Workbook

Sheet Dashboard
Z1: January
B2: PERSONAL FINANCE DASHBOARD | M2: July | Z2: February
Z3: March
Z4: April
B5: Total Income | E5: Total Expenses | H5: Total Savings | K5: Total Debt | N5: Budget Left | Z5: May
B6: {=INDIRECT("'"&$M$2&"'!I12")} | E6: {=INDIRECT("'"&$M$2&"'!I25")} | H6: {=INDIRECT("'"&$M$2&"'!D25")} | K6: {=INDIRECT("'"&$M$2&"'!S25")} | N6: {=INDIRECT("'"&$M$2&"'!D12")} | Z6: June
Z7: July
Z8: August
Z9: September
V10: Category | W10: Actual | Z10: October
V11: Bus | W11: {=INDIRECT("'"&$M$2&"'!I16")} | Z11: November
N12: Metric | O12: Formula | P12: Output | V12: Uber/Rapido | W12: {=INDIRECT("'"&$M$2&"'!I17")} | Z12: December
N13: Savings Rate | O13: Savings ÷ Income | P13: =H6/B6 | V13: Dining Out | W13: {=INDIRECT("'"&$M$2&"'!I18")}
N14: Expense Ratio | O14: Expenses ÷ Income | P14: =E6/B6 | V14: Other Expenses | W14: {=INDIRECT("'"&$M$2&"'!I19")}
N15: Debt Ratio | O15: Debt ÷ Income | P15: =K6/B6 | V15: Food Outside | W15: {=INDIRECT("'"&$M$2&"'!I20")}
N16: Budget Utilization | O16: Expenses ÷ Budget | P16: {=E6/INDIRECT("'"&$M$2&"'!H25")} | V16: Food Order | W16: {=INDIRECT("'"&$M$2&"'!I21")}
V19: Month | W19: Balance
V20: January | W20: =January!D12
V21: February | W21: =February!D12
V22: March | W22: =March!D12
V23: April | W23: =April!D12
V24: May | W24: =May!D12
J25: Financial Insights | V25: June | W25: =June!D12
V26: July | W26: =July!D12
J27: ✔ Savings Rate: 19.0% | V27: August | W27: =August!D12
V28: September | W28: =September!D12
J29: ✔ Largest Expense: | V29: October | W29: =October!D12
J30: Bills | V30: November | W30: =November!D12
V31: December | W31: =December!D12
J32: ✔ Budget Status:
J33: Under Budget
V34: A | W34: B | X34: C
J35: ✔ Net Balance: | V35: Category | W35: Budget | X35: Actual
J36: 39400 | V36: Income | W36: {=INDIRECT("'"&$M$2&"'!H12")} | X36: {=INDIRECT("'"&$M$2&"'!I12")}
V37: Expenses | W37: {=INDIRECT("'"&$M$2&"'!H25")} | X37: {=INDIRECT("'"&$M$2&"'!I25")}
V38: Bills | W38: {=INDIRECT("'"&$M$2&"'!M25")} | X38: {=INDIRECT("'"&$M$2&"'!N25")}
V39: Savings | W39: {=INDIRECT("'"&$M$2&"'!C25")} | X39: {=INDIRECT("'"&$M$2&"'!D25")}
V40: Debt | W40: {=INDIRECT("'"&$M$2&"'!R25")} | X40: {=INDIRECT("'"&$M$2&"'!S25")}

Sheet Sheet1

Sheet January
B2: January | F2: Income
B3: Monthly Budget | G3: Date | H3: Budget | I3: Actual
F4: Pay Check | H4: 65000 | I4: 65000
B5: Cash Flow | F5: Other Income | H5: 3000 | I5: 6250
C6: Budget | D6: Actual
B7: Start Balance | C7: 8000 | D7: 8000 | K7: =C12 | P7: =D12
B8: Income | C8: 68000 | D8: 71250
B9: Expense | C9: 18500 | D9: 19350
B10: Debt | C10: 7000 | D10: 7000
B11: Savings | C11: 12000 | D11: 13500
B12: Balance | C12: =C7+C8-C9-C10-C11 | D12: =D7+D8-D9-D10-D11 | F12: Balance | H12: =SUM(H4:H11) | I12: =SUM(I4:I11)
B13: Spent | C13: =SUM(C9:C12) | D13: =SUM(D9:D12)
B14: Savings & Investments | F14: Expenses | K14: Bills | P14: Debts
C15: Budget | D15: Actual | G15: Date | H15: Budget | I15: Actual | L15: Date | M15: Budget | N15: Actual | Q15: Date | R15: Budget | S15: Actual
B16: Emergency | C16: 5000 | D16: 5000 | F16: Bus | H16: 1500 | I16: 1350 | K16: Rent | M16: 15000 | N16: 15000 | P16: Visa Card | R16: 2500 | S16: 2500
B17: Vacation | C17: 2000 | D17: 1500 | F17: Uber/Rapido | H17: 2500 | I17: 2900 | K17: Electricity | M17: 2000 | N17: 2250 | P17: Mastercaard | R17: 2000 | S17: 2000
B18: Other | C18: 1000 | D18: 800 | F18: Dining Out | H18: 3500 | I18: 4100 | K18: Cell Phone | M18: 800 | N18: 799 | P18: Personal Loan | R18: 2500 | S18: 2500
B19: Investment | C19: 4000 | D19: 6200 | F19: Other Expenses | H19: 2000 | I19: 1700 | K19: Internet | M19: 1000 | N19: 999
F20: Food Outside | H20: 4000 | I20: 4350 | K20: Bus Pass | M20: 1200 | N20: 1200
F21: Food Order | H21: 5000 | I21: 4950
B25: Balance | C25: =SUM(C16:C24) | D25: =SUM(D16:D24) | F25: Balance | H25: =SUM(H16:H24) | I25: =SUM(I16:I24) | K25: Balance | M25: =SUM(M16:M20) | N25: =SUM(N16:N20) | P25: Balance | R25: =SUM(R16:R24) | S25: =SUM(S16:S24)

Sheet February
B2: February | F2: Income
B3: Monthly Budget | G3: Date | H3: Budget | I3: Actual
F4: Pay Check | H4: 65000 | I4: 6000
B5: Cash Flow | F5: Other Income | H5: 3000 | I5: 6250
C6: Budget | D6: Actual
B7: Start Balance | C7: 8000 | D7: 12000 | K7: =C12 | P7: =D12
B8: Income | C8: 68000 | D8: 71250
B9: Expense | C9: 18500 | D9: 19350
B10: Debt | C10: 7000 | D10: 7000
B11: Savings | C11: 12000 | D11: 13500
B12: Balance | C12: =C7+C8-C9-C10-C11 | D12: =D7+D8-D9-D10-D11 | F12: Balance | H12: =SUM(H4:H11) | I12: =SUM(I4:I11)
B13: Spent | C13: =SUM(C9:C12) | D13: =SUM(D9:D12)
B14: Savings & Investments | F14: Expenses | K14: Bills | P14: Debts
C15: Budget | D15: Actual | G15: Date | H15: Budget | I15: Actual | L15: Date | M15: Budget | N15: Actual | Q15: Date | R15: Budget | S15: Actual
B16: Emergency | C16: 5000 | D16: 5000 | F16: Bus | H16: 1500 | I16: 1350 | K16: Rent | M16: 15000 | N16: 15000 | P16: Visa Card | R16: 2500 | S16: 2500
B17: Vacation | C17: 2000 | D17: 1500 | F17: Uber/Rapido | H17: 2500 | I17: 2900 | K17: Electricity | M17: 2000 | N17: 2250 | P17: Mastercaard | R17: 2000 | S17: 2000
B18: Other | C18: 1000 | D18: 800 | F18: Dining Out | H18: 3500 | I18: 4100 | K18: Cell Phone | M18: 800 | N18: 799 | P18: Personal Loan | R18: 2500 | S18: 2500
B19: Investment | C19: 4000 | D19: 6200 | F19: Other Expenses | H19: 2000 | I19: 1700 | K19: Internet | M19: 1000 | N19: 999
F20: Food Outside | H20: 4000 | I20: 4350 | K20: Bus Pass | M20: 1200 | N20: 1200
F21: Food Order | H21: 5000 | I21: 4950
B25: Balance | C25: =SUM(C16:C24) | D25: =SUM(D16:D24) | F25: Balance | H25: =SUM(H16:H24) | I25: =SUM(I16:I24) | K25: Balance | M25: =SUM(M16:M20) | N25: =SUM(N16:N20) | P25: Balance | R25: =SUM(R16:R24) | S25: =SUM(S16:S24)

Sheet March
B2: March | F2: Income
B3: Monthly Budget | G3: Date | H3: Budget | I3: Actual
F4: Pay Check | H4: 65000 | I4: 65000
B5: Cash Flow | F5: Other Income | H5: 3000 | I5: 6250
C6: Budget | D6: Actual
B7: Start Balance | C7: 8000 | D7: 15000 | K7: =C12 | P7: =D12
B8: Income | C8: 68000 | D8: 71250
B9: Expense | C9: 18500 | D9: 19350
B10: Debt | C10: 7000 | D10: 7000
B11: Savings | C11: 12000 | D11: 13500
B12: Balance | C12: =C7+C8-C9-C10-C11 | D12: =D7+D8-D9-D10-D11 | F12: Balance | H12: =SUM(H4:H11) | I12: =SUM(I4:I11)
B13: Spent | C13: =SUM(C9:C12) | D13: =SUM(D9:D12)
B14: Savings & Investments | F14: Expenses | K14: Bills | P14: Debts
C15: Budget | D15: Actual | G15: Date | H15: Budget | I15: Actual | L15: Date | M15: Budget | N15: Actual | Q15: Date | R15: Budget | S15: Actual
B16: Emergency | C16: 5000 | D16: 5000 | F16: Bus | H16: 1500 | I16: 1350 | K16: Rent | M16: 15000 | N16: 15000 | P16: Visa Card | R16: 2500 | S16: 2500
B17: Vacation | C17: 2000 | D17: 1500 | F17: Uber/Rapido | H17: 2500 | I17: 2900 | K17: Electricity | M17: 2000 | N17: 2250 | P17: Mastercaard | R17: 2000 | S17: 2000
B18: Other | C18: 1000 | D18: 800 | F18: Dining Out | H18: 3500 | I18: 4100 | K18: Cell Phone | M18: 800 | N18: 799 | P18: Personal Loan | R18: 2500 | S18: 2500
B19: Investment | C19: 4000 | D19: 6200 | F19: Other Expenses | H19: 2000 | I19: 1700 | K19: Internet | M19: 1000 | N19: 999
F20: Food Outside | H20: 4000 | I20: 4350 | K20: Bus Pass | M20: 1200 | N20: 1200
F21: Food Order | H21: 5000 | I21: 4950
B25: Balance | C25: =SUM(C16:C24) | D25: =SUM(D16:D24) | F25: Balance | H25: =SUM(H16:H24) | I25: =SUM(I16:I24) | K25: Balance | M25: =SUM(M16:M20) | N25: =SUM(N16:N20) | P25: Balance | R25: =SUM(R16:R24) | S25: =SUM(S16:S24)

Sheet April
B2: April | F2: Income
B3: Monthly Budget | G3: Date | H3: Budget | I3: Actual
F4: Pay Check | H4: 65000 | I4: 65000
B5: Cash Flow | F5: Other Income | H5: 3000 | I5: 6250
C6: Budget | D6: Actual
B7: Start Balance | C7: 8000 | D7: 6000 | K7: =C12 | P7: =D12
B8: Income | C8: 68000 | D8: 71250
B9: Expense | C9: 18500 | D9: 19350
B10: Debt | C10: 7000 | D10: 7000
B11: Savings | C11: 12000 | D11: 13500
B12: Balance | C12: =C7+C8-C9-C10-C11 | D12: =D7+D8-D9-D10-D11 | F12: Balance | H12: =SUM(H4:H11) | I12: =SUM(I4:I11)
B13: Spent | C13: =SUM(C9:C12) | D13: =SUM(D9:D12)
B14: Savings & Investments | F14: Expenses | K14: Bills | P14: Debts
C15: Budget | D15: Actual | G15: Date | H15: Budget | I15: Actual | L15: Date | M15: Budget | N15: Actual | Q15: Date | R15: Budget | S15: Actual
B16: Emergency | C16: 5000 | D16: 5000 | F16: Bus | H16: 1500 | I16: 1350 | K16: Rent | M16: 15000 | N16: 15000 | P16: Visa Card | R16: 2500 | S16: 2500
B17: Vacation | C17: 2000 | D17: 1500 | F17: Uber/Rapido | H17: 2500 | I17: 2900 | K17: Electricity | M17: 2000 | N17: 2250 | P17: Mastercaard | R17: 2000 | S17: 2000
B18: Other | C18: 1000 | D18: 800 | F18: Dining Out | H18: 3500 | I18: 4100 | K18: Cell Phone | M18: 800 | N18: 799 | P18: Personal Loan | R18: 2500 | S18: 2500
B19: Investment | C19: 4000 | D19: 6200 | F19: Other Expenses | H19: 2000 | I19: 1700 | K19: Internet | M19: 1000 | N19: 999
F20: Food Outside | H20: 4000 | I20: 4350 | K20: Bus Pass | M20: 1200 | N20: 1200
F21: Food Order | H21: 5000 | I21: 4950
B25: Balance | C25: =SUM(C16:C24) | D25: =SUM(D16:D24) | F25: Balance | H25: =SUM(H16:H24) | I25: =SUM(I16:I24) | K25: Balance | M25: =SUM(M16:M20) | N25: =SUM(N16:N20) | P25: Balance | R25: =SUM(R16:R24) | S25: =SUM(S16:S24)

Sheet May
B2: May | F2: Income
B3: Monthly Budget | G3: Date | H3: Budget | I3: Actual
F4: Pay Check | H4: 65000 | I4: 65000
B5: Cash Flow | F5: Other Income | H5: 3000 | I5: 6250
C6: Budget | D6: Actual
B7: Start Balance | C7: 8000 | D7: 9000 | K7: =C12 | P7: =D12
B8: Income | C8: 68000 | D8: 71250
B9: Expense | C9: 18500 | D9: 19350
B10: Debt | C10: 7000 | D10: 7000
B11: Savings | C11: 12000 | D11: 13500
B12: Balance | C12: =C7+C8-C9-C10-C11 | D12: =D7+D8-D9-D10-D11 | F12: Balance | H12: =SUM(H4:H11) | I12: =SUM(I4:I11)
B13: Spent | C13: =SUM(C9:C12) | D13: =SUM(D9:D12)
B14: Savings & Investments | F14: Expenses | K14: Bills | P14: Debts
C15: Budget | D15: Actual | G15: Date | H15: Budget | I15: Actual | L15: Date | M15: Budget | N15: Actual | Q15: Date | R15: Budget | S15: Actual
B16: Emergency | C16: 5000 | D16: 5000 | F16: Bus | H16: 1500 | I16: 1350 | K16: Rent | M16: 15000 | N16: 15000 | P16: Visa Card | R16: 2500 | S16: 2500
B17: Vacation | C17: 2000 | D17: 1500 | F17: Uber/Rapido | H17: 2500 | I17: 2900 | K17: Electricity | M17: 2000 | N17: 2250 | P17: Mastercaard | R17: 2000 | S17: 2000
B18: Other | C18: 1000 | D18: 800 | F18: Dining Out | H18: 3500 | I18: 4100 | K18: Cell Phone | M18: 800 | N18: 799 | P18: Personal Loan | R18: 2500 | S18: 2500
B19: Investment | C19: 4000 | D19: 6200 | F19: Other Expenses | H19: 2000 | I19: 1700 | K19: Internet | M19: 1000 | N19: 999
F20: Food Outside | H20: 4000 | I20: 4350 | K20: Bus Pass | M20: 1200 | N20: 1200
F21: Food Order | H21: 5000 | I21: 4950
B25: Balance | C25: =SUM(C16:C24) | D25: =SUM(D16:D24) | F25: Balance | H25: =SUM(H16:H24) | I25: =SUM(I16:I24) | K25: Balance | M25: =SUM(M16:M20) | N25: =SUM(N16:N20) | P25: Balance | R25: =SUM(R16:R24) | S25: =SUM(S16:S24)

Sheet June
B2: June | F2: Income
B3: Monthly Budget | G3: Date | H3: Budget | I3: Actual
F4: Pay Check | H4: 65000 | I4: 65000
B5: Cash Flow | F5: Other Income | H5: 3000 | I5: 6250
C6: Budget | D6: Actual
B7: Start Balance | C7: 8000 | D7: 10000 | K7: =C12 | P7: =D12
B8: Income | C8: 68000 | D8: 71250
B9: Expense | C9: 18500 | D9: 19350
B10: Debt | C10: 7000 | D10: 7000
B11: Savings | C11: 12000 | D11: 13500
B12: Balance | C12: =C7+C8-C9-C10-C11 | D12: =D7+D8-D9-D10-D11 | F12: Balance | H12: =SUM(H4:H11) | I12: =SUM(I4:I11)
B13: Spent | C13: =SUM(C9:C12) | D13: =SUM(D9:D12)
B14: Savings & Investments | F14: Expenses | K14: Bills | P14: Debts
C15: Budget | D15: Actual | G15: Date | H15: Budget | I15: Actual | L15: Date | M15: Budget | N15: Actual | Q15: Date | R15: Budget | S15: Actual
B16: Emergency | C16: 5000 | D16: 5000 | F16: Bus | H16: 1500 | I16: 1350 | K16: Rent | M16: 15000 | N16: 15000 | P16: Visa Card | R16: 2500 | S16: 2500
B17: Vacation | C17: 2000 | D17: 1500 | F17: Uber/Rapido | H17: 2500 | I17: 2900 | K17: Electricity | M17: 2000 | N17: 2250 | P17: Mastercaard | R17: 2000 | S17: 2000
B18: Other | C18: 1000 | D18: 800 | F18: Dining Out | H18: 3500 | I18: 4100 | K18: Cell Phone | M18: 800 | N18: 799 | P18: Personal Loan | R18: 2500 | S18: 2500
B19: Investment | C19: 4000 | D19: 6200 | F19: Other Expenses | H19: 2000 | I19: 1700 | K19: Internet | M19: 1000 | N19: 999
F20: Food Outside | H20: 4000 | I20: 4350 | K20: Bus Pass | M20: 1200 | N20: 1200
F21: Food Order | H21: 5000 | I21: 4950
B25: Balance | C25: =SUM(C16:C24) | D25: =SUM(D16:D24) | F25: Balance | H25: =SUM(H16:H24) | I25: =SUM(I16:I24) | K25: Balance | M25: =SUM(M16:M20) | N25: =SUM(N16:N20) | P25: Balance | R25: =SUM(R16:R24) | S25: =SUM(S16:S24)

Sheet July
B2: July | F2: Income
B3: Monthly Budget | G3: Date | H3: Budget | I3: Actual
F4: Pay Check | H4: 65000 | I4: 65000
B5: Cash Flow | F5: Other Income | H5: 3000 | I5: 6250
C6: Budget | D6: Actual
B7: Start Balance | C7: 8000 | D7: 12000 | K7: =C12 | P7: =D12
B8: Income | C8: 68000 | D8: 71250
B9: Expense | C9: 18500 | D9: 19350
B10: Debt | C10: 7000 | D10: 7000
B11: Savings | C11: 12000 | D11: 13500
B12: Balance | C12: =C7+C8-C9-C10-C11 | D12: =D7+D8-D9-D10-D11 | F12: Balance | H12: =SUM(H4:H11) | I12: =SUM(I4:I11)
B13: Spent | C13: =SUM(C9:C12) | D13: =SUM(D9:D12)
B14: Savings & Investments | F14: Expenses | K14: Bills | P14: Debts
C15: Budget | D15: Actual | G15: Date | H15: Budget | I15: Actual | L15: Date | M15: Budget | N15: Actual | Q15: Date | R15: Budget | S15: Actual
B16: Emergency | C16: 5000 | D16: 5000 | F16: Bus | H16: 1500 | I16: 1350 | K16: Rent | M16: 15000 | N16: 15000 | P16: Visa Card | R16: 2500 | S16: 2500
B17: Vacation | C17: 2000 | D17: 1500 | F17: Uber/Rapido | H17: 2500 | I17: 2900 | K17: Electricity | M17: 2000 | N17: 2250 | P17: Mastercaard | R17: 2000 | S17: 2000
B18: Other | C18: 1000 | D18: 800 | F18: Dining Out | H18: 3500 | I18: 4100 | K18: Cell Phone | M18: 800 | N18: 799 | P18: Personal Loan | R18: 2500 | S18: 2500
B19: Investment | C19: 4000 | D19: 6200 | F19: Other Expenses | H19: 2000 | I19: 1700 | K19: Internet | M19: 1000 | N19: 999
F20: Food Outside | H20: 4000 | I20: 4350 | K20: Bus Pass | M20: 1200 | N20: 1200
F21: Food Order | H21: 5000 | I21: 4950
B25: Balance | C25: =SUM(C16:C24) | D25: =SUM(D16:D24) | F25: Balance | H25: =SUM(H16:H24) | I25: =SUM(I16:I24) | K25: Balance | M25: =SUM(M16:M20) | N25: =SUM(N16:N20) | P25: Balance | R25: =SUM(R16:R24) | S25: =SUM(S16:S24)

Sheet August
B2: August | F2: Income
B3: Monthly Budget | G3: Date | H3: Budget | I3: Actual
F4: Pay Check | H4: 65000 | I4: 65000
B5: Cash Flow | F5: Other Income | H5: 3000 | I5: 6250
C6: Budget | D6: Actual
B7: Start Balance | C7: 8000 | D7: 3000 | K7: =C12 | P7: =D12
B8: Income | C8: 68000 | D8: 71250
B9: Expense | C9: 18500 | D9: 19350
B10: Debt | C10: 7000 | D10: 7000
B11: Savings | C11: 12000 | D11: 13500
B12: Balance | C12: =C7+C8-C9-C10-C11 | D12: =D7+D8-D9-D10-D11 | F12: Balance | H12: =SUM(H4:H11) | I12: =SUM(I4:I11)
B13: Spent | C13: =SUM(C9:C12) | D13: =SUM(D9:D12)
B14: Savings & Investments | F14: Expenses | K14: Bills | P14: Debts
C15: Budget | D15: Actual | G15: Date | H15: Budget | I15: Actual | L15: Date | M15: Budget | N15: Actual | Q15: Date | R15: Budget | S15: Actual
B16: Emergency | C16: 5000 | D16: 5000 | F16: Bus | H16: 1500 | I16: 1350 | K16: Rent | M16: 15000 | N16: 15000 | P16: Visa Card | R16: 2500 | S16: 2500
B17: Vacation | C17: 2000 | D17: 1500 | F17: Uber/Rapido | H17: 2500 | I17: 2900 | K17: Electricity | M17: 2000 | N17: 2250 | P17: Mastercaard | R17: 2000 | S17: 2000
B18: Other | C18: 1000 | D18: 800 | F18: Dining Out | H18: 3500 | I18: 4100 | K18: Cell Phone | M18: 800 | N18: 799 | P18: Personal Loan | R18: 2500 | S18: 2500
B19: Investment | C19: 4000 | D19: 6200 | F19: Other Expenses | H19: 2000 | I19: 1700 | K19: Internet | M19: 1000 | N19: 999
F20: Food Outside | H20: 4000 | I20: 4350 | K20: Bus Pass | M20: 1200 | N20: 1200
F21: Food Order | H21: 5000 | I21: 4950
B25: Balance | C25: =SUM(C16:C24) | D25: =SUM(D16:D24) | F25: Balance | H25: =SUM(H16:H24) | I25: =SUM(I16:I24) | K25: Balance | M25: =SUM(M16:M20) | N25: =SUM(N16:N20) | P25: Balance | R25: =SUM(R16:R24) | S25: =SUM(S16:S24)

Sheet September
B2: September | F2: Income
B3: Monthly Budget | G3: Date | H3: Budget | I3: Actual
F4: Pay Check | H4: 65000 | I4: 65000
B5: Cash Flow | F5: Other Income | H5: 3000 | I5: 6250
C6: Budget | D6: Actual
B7: Start Balance | C7: 8000 | D7: 6200 | K7: =C12 | P7: =D12
B8: Income | C8: 68000 | D8: 71250
B9: Expense | C9: 18500 | D9: 19350
B10: Debt | C10: 7000 | D10: 7000
B11: Savings | C11: 12000 | D11: 13500
B12: Balance | C12: =C7+C8-C9-C10-C11 | D12: =D7+D8-D9-D10-D11 | F12: Balance | H12: =SUM(H4:H11) | I12: =SUM(I4:I11)
B13: Spent | C13: =SUM(C9:C12) | D13: =SUM(D9:D12)
B14: Savings & Investments | F14: Expenses | K14: Bills | P14: Debts
C15: Budget | D15: Actual | G15: Date | H15: Budget | I15: Actual | L15: Date | M15: Budget | N15: Actual | Q15: Date | R15: Budget | S15: Actual
B16: Emergency | C16: 5000 | D16: 5000 | F16: Bus | H16: 1500 | I16: 1350 | K16: Rent | M16: 15000 | N16: 15000 | P16: Visa Card | R16: 2500 | S16: 2500
B17: Vacation | C17: 2000 | D17: 1500 | F17: Uber/Rapido | H17: 2500 | I17: 2900 | K17: Electricity | M17: 2000 | N17: 2250 | P17: Mastercaard | R17: 2000 | S17: 2000
B18: Other | C18: 1000 | D18: 800 | F18: Dining Out | H18: 3500 | I18: 4100 | K18: Cell Phone | M18: 800 | N18: 799 | P18: Personal Loan | R18: 2500 | S18: 2500
B19: Investment | C19: 4000 | D19: 6200 | F19: Other Expenses | H19: 2000 | I19: 1700 | K19: Internet | M19: 1000 | N19: 999
F20: Food Outside | H20: 4000 | I20: 4350 | K20: Bus Pass | M20: 1200 | N20: 1200
F21: Food Order | H21: 5000 | I21: 4950
B25: Balance | C25: =SUM(C16:C24) | D25: =SUM(D16:D24) | F25: Balance | H25: =SUM(H16:H24) | I25: =SUM(I16:I24) | K25: Balance | M25: =SUM(M16:M20) | N25: =SUM(N16:N20) | P25: Balance | R25: =SUM(R16:R24) | S25: =SUM(S16:S24)

Sheet October
B2: October | F2: Income
B3: Monthly Budget | G3: Date | H3: Budget | I3: Actual
F4: Pay Check | H4: 65000 | I4: 65000
B5: Cash Flow | F5: Other Income | H5: 3000 | I5: 6250
C6: Budget | D6: Actual
B7: Start Balance | C7: 8000 | D7: 8900 | K7: =C12 | P7: =D12
B8: Income | C8: 68000 | D8: 71250
B9: Expense | C9: 18500 | D9: 19350
B10: Debt | C10: 7000 | D10: 7000
B11: Savings | C11: 12000 | D11: 13500
B12: Balance | C12: =C7+C8-C9-C10-C11 | D12: =D7+D8-D9-D10-D11 | F12: Balance | H12: =SUM(H4:H11) | I12: =SUM(I4:I11)
B13: Spent | C13: =SUM(C9:C12) | D13: =SUM(D9:D12)
B14: Savings & Investments | F14: Expenses | K14: Bills | P14: Debts
C15: Budget | D15: Actual | G15: Date | H15: Budget | I15: Actual | L15: Date | M15: Budget | N15: Actual | Q15: Date | R15: Budget | S15: Actual
B16: Emergency | C16: 5000 | D16: 5000 | F16: Bus | H16: 1500 | I16: 1350 | K16: Rent | M16: 15000 | N16: 15000 | P16: Visa Card | R16: 2500 | S16: 2500
B17: Vacation | C17: 2000 | D17: 1500 | F17: Uber/Rapido | H17: 2500 | I17: 2900 | K17: Electricity | M17: 2000 | N17: 2250 | P17: Mastercaard | R17: 2000 | S17: 2000
B18: Other | C18: 1000 | D18: 800 | F18: Dining Out | H18: 3500 | I18: 4100 | K18: Cell Phone | M18: 800 | N18: 799 | P18: Personal Loan | R18: 2500 | S18: 2500
B19: Investment | C19: 4000 | D19: 6200 | F19: Other Expenses | H19: 2000 | I19: 1700 | K19: Internet | M19: 1000 | N19: 999
F20: Food Outside | H20: 4000 | I20: 4350 | K20: Bus Pass | M20: 1200 | N20: 1200
F21: Food Order | H21: 5000 | I21: 4950
B25: Balance | C25: =SUM(C16:C24) | D25: =SUM(D16:D24) | F25: Balance | H25: =SUM(H16:H24) | I25: =SUM(I16:I24) | K25: Balance | M25: =SUM(M16:M20) | N25: =SUM(N16:N20) | P25: Balance | R25: =SUM(R16:R24) | S25: =SUM(S16:S24)

Sheet November
B2: November | F2: Income
B3: Monthly Budget | G3: Date | H3: Budget | I3: Actual
F4: Pay Check | H4: 65000 | I4: 65000
B5: Cash Flow | F5: Other Income | H5: 3000 | I5: 6250
C6: Budget | D6: Actual
B7: Start Balance | C7: 8000 | D7: 9600 | K7: =C12 | P7: =D12
B8: Income | C8: 68000 | D8: 71250
B9: Expense | C9: 18500 | D9: 19350
B10: Debt | C10: 7000 | D10: 7000
B11: Savings | C11: 12000 | D11: 13500
B12: Balance | C12: =C7+C8-C9-C10-C11 | D12: =D7+D8-D9-D10-D11 | F12: Balance | H12: =SUM(H4:H11) | I12: =SUM(I4:I11)
B13: Spent | C13: =SUM(C9:C12) | D13: =SUM(D9:D12)
B14: Savings & Investments | F14: Expenses | K14: Bills | P14: Debts
C15: Budget | D15: Actual | G15: Date | H15: Budget | I15: Actual | L15: Date | M15: Budget | N15: Actual | Q15: Date | R15: Budget | S15: Actual
B16: Emergency | C16: 5000 | D16: 5000 | F16: Bus | H16: 1500 | I16: 1350 | K16: Rent | M16: 15000 | N16: 15000 | P16: Visa Card | R16: 2500 | S16: 2500
B17: Vacation | C17: 2000 | D17: 1500 | F17: Uber/Rapido | H17: 2500 | I17: 2900 | K17: Electricity | M17: 2000 | N17: 2250 | P17: Mastercaard | R17: 2000 | S17: 2000
B18: Other | C18: 1000 | D18: 800 | F18: Dining Out | H18: 3500 | I18: 4100 | K18: Cell Phone | M18: 800 | N18: 799 | P18: Personal Loan | R18: 2500 | S18: 2500
B19: Investment | C19: 4000 | D19: 6200 | F19: Other Expenses | H19: 2000 | I19: 1700 | K19: Internet | M19: 1000 | N19: 999
F20: Food Outside | H20: 4000 | I20: 4350 | K20: Bus Pass | M20: 1200 | N20: 1200
F21: Food Order | H21: 5000 | I21: 4950
B25: Balance | C25: =SUM(C16:C24) | D25: =SUM(D16:D24) | F25: Balance | H25: =SUM(H16:H24) | I25: =SUM(I16:I24) | K25: Balance | M25: =SUM(M16:M20) | N25: =SUM(N16:N20) | P25: Balance | R25: =SUM(R16:R24) | S25: =SUM(S16:S24)

Sheet December
B2: December | F2: Income
B3: Monthly Budget | G3: Date | H3: Budget | I3: Actual
F4: Pay Check | H4: 65000 | I4: 65000
B5: Cash Flow | F5: Other Income | H5: 3000 | I5: 6250
C6: Budget | D6: Actual
B7: Start Balance | C7: 8000 | D7: 12400 | K7: =C12 | P7: =D12
B8: Income | C8: 68000 | D8: 71250
B9: Expense | C9: 18500 | D9: 19350
B10: Debt | C10: 7000 | D10: 7000
B11: Savings | C11: 12000 | D11: 13500
B12: Balance | C12: =C7+C8-C9-C10-C11 | D12: =D7+D8-D9-D10-D11 | F12: Balance | H12: =SUM(H4:H11) | I12: =SUM(I4:I11)
B13: Spent | C13: =SUM(C9:C12) | D13: =SUM(D9:D12)
B14: Savings & Investments | F14: Expenses | K14: Bills | P14: Debts
C15: Budget | D15: Actual | G15: Date | H15: Budget | I15: Actual | L15: Date | M15: Budget | N15: Actual | Q15: Date | R15: Budget | S15: Actual
B16: Emergency | C16: 5000 | D16: 5000 | F16: Bus | H16: 1500 | I16: 1350 | K16: Rent | M16: 15000 | N16: 15000 | P16: Visa Card | R16: 2500 | S16: 2500
B17: Vacation | C17: 2000 | D17: 1500 | F17: Uber/Rapido | H17: 2500 | I17: 2900 | K17: Electricity | M17: 2000 | N17: 2250 | P17: Mastercaard | R17: 2000 | S17: 2000
B18: Other | C18: 1000 | D18: 800 | F18: Dining Out | H18: 3500 | I18: 4100 | K18: Cell Phone | M18: 800 | N18: 799 | P18: Personal Loan | R18: 2500 | S18: 2500
B19: Investment | C19: 4000 | D19: 6200 | F19: Other Expenses | H19: 2000 | I19: 1700 | K19: Internet | M19: 1000 | N19: 999
F20: Food Outside | H20: 4000 | I20: 4350 | K20: Bus Pass | M20: 1200 | N20: 1200
F21: Food Order | H21: 5000 | I21: 4950
B25: Balance | C25: =SUM(C16:C24) | D25: =SUM(D16:D24) | F25: Balance | H25: =SUM(H16:H24) | I25: =SUM(I16:I24) | K25: Balance | M25: =SUM(M16:M20) | N25: =SUM(N16:N20) | P25: Balance | R25: =SUM(R16:R24) | S25: =SUM(S16:S24)

Sheet Transactions
A1: A | B1: B | C1: C | D1: D | E1: E | F1: F | G1: G | H1: H | I1: I
A2: ---------------------------------------------------------------------------------------------------------------------------------------------------------------------
A3: Date | B3: Type | C3: Category | D3: Merchant | E3: Amount | F3: Description | G3: AI Confidence | H3: Month | I3: Year
A4: 2026-07-14 | B4: Expense | C4: Food | D4: Domino's | E4: 450 | F4: Pizza | G4: 0.99 | H4: July | I4: 2026
A5: 2026-07-14 | B5: Expense | C5: Food | D5: Domino's | E5: 450 | F5: Pizza | G5: 0.99 | H5: July | I5: 2026
A6: 2026-07-14 | B6: Expense | C6: Food | D6: Domino's | E6: 450 | F6: Pizza | G6: 0.99 | H6: July | I6: 2026
A7: today | B7: Expense | C7: Dining Out | D7: Domino's | E7: 450 | F7: Spent ₹450 on Domino's today | G7: 0.99 | H7: None
A8: today | B8: Expense | C8: Dining Out | D8: Domino's | E8: 450 | F8: Spent ₹450 on Domino's today | G8: 0.99
A9: today | B9: Expense | C9: Dining Out | D9: Domino's | E9: 450 | F9: Spent ₹450 on Domino's today | G9: 0.99 | I9: 0
A10: today | B10: Expense | C10: Dining Out | D10: Domino's | E10: 450 | F10: Spent ₹450 on Domino's today | G10: 0.99 | H10: Unknown
A11: today | B11: Expense or Income | C11: Dining Out | D11: Domino's | E11: 450 | F11: Spent ₹450 on Domino's today | G11: 0.99 | H11: Unknown
A12: today | B12: Expense | C12: Dining Out | D12: Domino's | E12: 450 | F12: Spent ₹450 on Domino's today | G12: 0.99 | H12: Not specified
A13: today | B13: Expense or Income | C13: Dining Out | D13: Domino's | E13: 450 | F13: Spent ₹450 on Domino's today | G13: 0.99 | H13: unknown
A14: yesterday | B14: Expense | C14: Dining Out | D14: Domino's | E14: 450 | F14: Spent ₹450 on Domino's yesterday | G14: 0.99 | H14: July | I14: 2026
A15: today | B15: Expense | C15: Dining Out | D15: Domino's | E15: 5000 | F15: Spent ₹5000 on Domino's today | G15: 0.99 | H15: Not specified
A16: 15-07-2026 | B16: Other Expenses | C16: Dining Out | E16: 5000 | F16: hotel | G16: 0.99 | I16: 2026
A17: 15-07-2026 | B17: Expense | C17: Other Expenses | D17: Unspecified | E17: 2000 | G17: 0.99 | H17: July | I17: 2026
A18: 15-07-2026 | B18: Expense | C18: Other Expenses | D18: Unspecified | E18: 300 | G18: 0.99 | H18: July | I18: 2026
A19: 14-07-2026 | B19: Income | C19: Salary | D19: Boss | E19: 25000 | G19: 0.99 | H19: July | I19: 2026
A20: 15-07-2026 | B20: Expense | C20: Bus | D20: conductor | E20: 12 | G20: 0.99 | H20: July | I20: 2026
A21: 15-07-2026 | B21: Expense | C21: Bus | D21: Unspecified | E21: 25 | G21: 0.99 | H21: July | I21: 2026
A22: 15-07-2026 | B22: Savings | C22: Other Expenses | D22: Unspecified | E22: 10000 | G22: 0.99 | H22: July | I22: 2026
A23: 13-07-2026 | B23: Income | C23: Salary | D23: Employer | E23: 5000 | G23: 0.99 | H23: July | I23: 2026
A24: 15-07-2026 | B24: Expense | C24: Bus | D24: Unspecified | E24: 6 | G24: 0.99 | H24: July | I24: 2026
A25: 15-07-2026 | B25: Expense | C25: Other Expenses | D25: Unspecified | E25: 5000 | G25: 0.99 | H25: July | I25: 2026
A26: 16-07-2026 | B26: Expense | C26: bus | D26: Unspecified | E26: 1600 | G26: 0.99 | H26: July | I26: 2026
A27: 16-07-2026 | B27: Expense | C27: Bus | D27: Unspecified | E27: 12 | G27: 0.99 | H27: July | I27: 2026
A28: 16-07-2026 | B28: Expense | C28: Bus | D28: Unspecified | E28: 5000 | G28: 0.99 | H28: July | I28: 2026
... A34: 16-07-2026 | B34: Income | C34: Other Expenses | D34: Unspecified | E34: 1000 | G34: 0.99 | H34: July | I34: 2026
A35: 16-07-2026 | B35: Expense | C35: Food | D35: Pizza Hut | E35: 500 | F35: Pizza and garlic bread | G35: 0.99 | H35: July | I35: 2026
A36: 16-07-2026 | B36: Income | C36: Salary | D36: Unspecified | E36: 900 | F36: Salary Recieved | G36: 0.99 | H36: July | I36: 2026
A37: 16-07-2026 | B37: Expense | C37: Bus | D37: Unspecified | E37: 12 | F37: Bus ticket | G37: 0.99 | H37: July | I37: 2026
A38: 16-07-2026 | B38: Debt | C38: Loan | D38: Unspecified | E38: 100 | F38: Debt | G38: 0.99 | H38: July | I38: 2026
A39: 16-07-2026 | B39: Income | C39: Salary | D39: Unspecified | E39: 10000 | F39: Salary Recieved | G39: 0.99 | H39: July | I39: 2026
A40: 16-07-2026 | B40: Expense | C40: Bus | D40: Unspecified | E40: 6 | F40: Bus Ticket | G40: 0.99 | H40: July | I40: 2026
A41: 16-07-2026 | B41: Income | C41: Recieved from Parents | D41: Unspecified | E41: 5000 | G41: 0.99 | H41: July | I41: 2026
A42: 16-07-2026 | B42: Expense | C42: Other Expenses | D42: Unspecified | E42: 1000 | G42: 0.99 | H42: July | I42: 2026
A43: 16-07-2026 | B43: Expense | C43: Other Expenses | D43: Unspecified | E43: 1000 | G43: 0.99 | H43: January | I43: 2026
A44: 16-07-2026 | B44: Income | C44: Other Expenses | D44: Unspecified | E44: 5000 | G44: 0.99 | H44: January | I44: 2026
A45: 16-07-2026 | B45: Expense | C45: Bus | D45: Unspecified | E45: 20 | G45: 0.99 | H45: January | I45: 2026
